README.md
pyproject.toml
yaar.py
yaar.egg-info/PKG-INFO
yaar.egg-info/SOURCES.txt
yaar.egg-info/dependency_links.txt
yaar.egg-info/requires.txt
yaar.egg-info/top_level.txt