Metadata-Version: 2.1
Name: yaar
Version: 0.3.1
Summary: Yet Another Asyncio Requets
Author: Juca Crispim
Classifier: Development Status :: 4 - Beta
Classifier: Environment :: Console
Classifier: Intended Audience :: Developers
Classifier: Operating System :: Unix
Classifier: Topic :: Software Development :: Quality Assurance
Classifier: Programming Language :: Python :: 3
